codicefiscale/__init__.py
codicefiscale/__main__.py
codicefiscale/cli.py
codicefiscale/codicefiscale.py
codicefiscale/data.py
codicefiscale/metadata.py
codicefiscale/py.typed
codicefiscale/data/countries-patch.json
codicefiscale/data/countries.json
codicefiscale/data/deleted-countries.json
codicefiscale/data/municipalities-patch.json
codicefiscale/data/municipalities.json
python_codicefiscale-0.11.3.dist-info/licenses/LICENSE.txt
python_codicefiscale-0.11.3.dist-info/METADATA
python_codicefiscale-0.11.3.dist-info/WHEEL
python_codicefiscale-0.11.3.dist-info/entry_points.txt
python_codicefiscale-0.11.3.dist-info/top_level.txt
python_codicefiscale-0.11.3.dist-info/RECORD
