Metadata-Version: 2.4
Name: python-codicefiscale
Version: 0.11.3
Summary: encode / decode italian fiscal codes - codifica / decodifica del Codice Fiscale italiano.
Author-email: Fabio Caccamo <fabio.caccamo@gmail.com>
Maintainer-email: Fabio Caccamo <fabio.caccamo@gmail.com>
License: MIT License
Project-URL: Homepage, https://github.com/fabiocaccamo/python-codicefiscale
Project-URL: Download, https://github.com/fabiocaccamo/python-codicefiscale/releases
Project-URL: Documentation, https://github.com/fabiocaccamo/python-codicefiscale#readme
Project-URL: Issues, https://github.com/fabiocaccamo/python-codicefiscale/issues
Project-URL: Funding, https://github.com/sponsors/fabiocaccamo/
Project-URL: Twitter, https://twitter.com/fabiocaccamo
Keywords: codicefiscale,codice,fiscale,cf,fiscal code,italia,italy
Classifier: Development Status :: 5 - Production/Stable
Classifier: Environment :: Web Environment
Classifier: Intended Audience :: Developers
Classifier: License :: OSI Approved :: MIT License
Classifier: Natural Language :: English
Classifier: Operating System :: OS Independent
Classifier: Programming Language :: Python :: 3
Classifier: Programming Language :: Python :: 3.10
Classifier: Programming Language :: Python :: 3.11
Classifier: Programming Language :: Python :: 3.12
Classifier: Programming Language :: Python :: 3.13
Classifier: Programming Language :: Python :: 3.14
Classifier: Programming Language :: Python :: Implementation :: PyPy
Classifier: Topic :: Software Development :: Build Tools
License-File: LICENSE.txt
Requires-Dist: python-dateutil<2.10,>=2.8
Requires-Dist: python-fsutil<1.0.0,>=0.16.0
Requires-Dist: python-slugify<9.0.0,>=7.0.0
Dynamic: license-file
